alphafilter/__init__.py
alphafilter/admin.py
alphafilter/models.py
alphafilter/sql.py
alphafilter/tests.py
alphafilter/views.py
alphafilter/templates/.DS_Store
alphafilter/templates/admin/.DS_Store
alphafilter/templates/admin/alphabet.html
alphafilter/templates/alphafilter/alphabet.html
alphafilter/templates/alphafilter/alphafilter_styles.html
alphafilter/templates/alphafilter/change_list.html
alphafilter/templates/alphafilter/test.html
alphafilter/templatetags/__init__.py
alphafilter/templatetags/alphafilter.py
django_alphafilter-1.0.dist-info/DESCRIPTION.rst
django_alphafilter-1.0.dist-info/METADATA
django_alphafilter-1.0.dist-info/RECORD
django_alphafilter-1.0.dist-info/WHEEL
django_alphafilter-1.0.dist-info/metadata.json
django_alphafilter-1.0.dist-info/top_level.txt
example/__init__.py
example/manage.py
example/settings.py
example/urls.py
example/testtags/__init__.py
example/testtags/admin.py
example/testtags/models.py
example/testtags/tests.py
example/testtags/views.py
