Metadata-Version: 2.0
Name: django-alphafilter
Version: 1.0
Summary: Django-AlphaFilter provides an admin widget for alphabetical filtering that works like date_hierarchy and an template tag for use elsewhere.
Home-page: http://github.com/coordt/django-alphabetfilter
Author: Corey Oordt
Author-email: coreyoordt@gmail.com
License: Apache 2.0
Platform: UNKNOWN
Requires-Dist: future (>=0.16.0)
